sllm/__init__.py
sllm/common.py
sllm/config.py
sllm/train.py
sllm/utils.py
sllm/nn/__init__.py
sllm/nn/autodiff.py
sllm/nn/layers.py
sllm/nn/transformer.py
sllm/ops/__init__.py
sllm/ops/matmul.cpython-311-darwin.so
sllm_lib-0.0.1.dist-info/licenses/LICENSE
sllm_lib-0.0.1.dist-info/METADATA
sllm_lib-0.0.1.dist-info/WHEEL
sllm_lib-0.0.1.dist-info/top_level.txt
sllm_lib-0.0.1.dist-info/RECORD
