Metadata-Version: 2.4
Name: sllm-lib
Version: 0.0.1
Summary: Super Lazy Language Model
Author: Henry Ndubuaku
Classifier: Programming Language :: Python :: 3
Classifier: License :: OSI Approved :: MIT License
Classifier: Operating System :: OS Independent
License-File: LICENSE
Requires-Dist: numpy
Requires-Dist: transformers
Requires-Dist: platformdirs
Requires-Dist: tqdm
Requires-Dist: pybind11
Dynamic: author
Dynamic: classifier
Dynamic: description
Dynamic: description-content-type
Dynamic: license-file
Dynamic: requires-dist
Dynamic: summary
